dl_matrix/__init__.py
dl_matrix/base.py
dl_matrix/builder.py
dl_matrix/context.py
dl_matrix/parsers.py
dl_matrix/relationship.py
dl_matrix/type.py
dl_matrix/utils.py
dl_matrix/chaintrees/__init__.py
dl_matrix/chaintrees/factory.py
dl_matrix/chaintrees/links.py
dl_matrix/chaintrees/symphony/__init__.py
dl_matrix/chaintrees/symphony/builder.py
dl_matrix/chaintrees/symphony/director.py
dl_matrix/chaintrees/symphony/system.py
dl_matrix/chaintrees/symphony/technique.py
dl_matrix/chaintrees/symphony/synthesis/__init__.py
dl_matrix/chaintrees/symphony/synthesis/base.py
dl_matrix/chaintrees/symphony/synthesis/chaos_theory.py
dl_matrix/chaintrees/symphony/synthesis/convergent_fusion.py
dl_matrix/chaintrees/symphony/synthesis/divergent_expansion.py
dl_matrix/chaintrees/symphony/synthesis/emergent_synthesis.py
dl_matrix/chaintrees/symphony/synthesis/eureka_elicitation.py
dl_matrix/chaintrees/symphony/synthesis/fractal_thinking.py
dl_matrix/chaintrees/symphony/synthesis/infinite_mind.py
dl_matrix/chaintrees/symphony/synthesis/manager.py
dl_matrix/chaintrees/symphony/synthesis/metaphysical_illumination.py
dl_matrix/chaintrees/symphony/synthesis/morphogenesis.py
dl_matrix/chaintrees/symphony/synthesis/non_linear_navigation.py
dl_matrix/chaintrees/symphony/synthesis/organic_synthesis.py
dl_matrix/chaintrees/symphony/synthesis/paradoxical_reflection.py
dl_matrix/chaintrees/symphony/synthesis/power_of_perspective.py
dl_matrix/chaintrees/symphony/synthesis/quantum_entanglement.py
dl_matrix/chaintrees/symphony/synthesis/radical_collaboration.py
dl_matrix/chaintrees/symphony/synthesis/synergetic_fusion.py
dl_matrix/embedding/__init__.py
dl_matrix/embedding/match.py
dl_matrix/embedding/spatial.py
dl_matrix/embedding/utils.py
dl_matrix/infrence/__init__.py
dl_matrix/infrence/base.py
dl_matrix/infrence/generator.py
dl_matrix/infrence/manager.py
dl_matrix/infrence/openai.py
dl_matrix/infrence/parallel.py
dl_matrix/infrence/session.py
dl_matrix/infrence/state.py
dl_matrix-3.3.dist-info/LICENSE
dl_matrix-3.3.dist-info/METADATA
dl_matrix-3.3.dist-info/WHEEL
dl_matrix-3.3.dist-info/top_level.txt
dl_matrix-3.3.dist-info/RECORD
