Metadata-Version: 2.1
Name: dl-matrix
Version: 3.3
Summary: A Divergent Language Matrix package
Home-page: http://github.com/diomandeee/dl_matrix
Author: Mohamed Diomande
Author-email: gdiomande7907@gmail.com
License: MIT
Keywords: divergent language matrix
Classifier: Development Status :: 3 - Alpha
Classifier: License :: OSI Approved :: MIT License
Classifier: Programming Language :: Python :: 3.6
Classifier: Programming Language :: Python :: 3.7
Classifier: Programming Language :: Python :: 3.8
Classifier: Programming Language :: Python :: 3.9
Requires-Python: >=3.6
License-File: LICENSE
Requires-Dist: aiohttp ==3.8.5
Requires-Dist: aiosignal ==1.3.1
Requires-Dist: ansi2html ==1.8.0
Requires-Dist: async-timeout ==4.0.3
Requires-Dist: attrs ==23.1.0
Requires-Dist: bleach ==6.0.0
Requires-Dist: certifi ==2023.7.22
Requires-Dist: charset-normalizer ==3.2.0
Requires-Dist: click ==8.1.6
Requires-Dist: Cython ==0.29.36
Requires-Dist: dash ==2.12.0
Requires-Dist: dash-core-components ==2.0.0
Requires-Dist: dash-html-components ==2.0.0
Requires-Dist: dash-table ==5.0.0
Requires-Dist: docutils ==0.20.1
Requires-Dist: filelock ==3.12.2
Requires-Dist: Flask ==2.2.5
Requires-Dist: frozenlist ==1.4.0
Requires-Dist: fsspec ==2023.6.0
Requires-Dist: hdbscan ==0.8.33
Requires-Dist: huggingface-hub ==0.16.4
Requires-Dist: idna ==3.4
Requires-Dist: importlib-metadata ==6.8.0
Requires-Dist: itsdangerous ==2.1.2
Requires-Dist: jaraco.classes ==3.3.0
Requires-Dist: Jinja2 ==3.1.2
Requires-Dist: joblib ==1.3.2
Requires-Dist: keyring ==24.2.0
Requires-Dist: llvmlite ==0.40.1
Requires-Dist: markdown-it-py ==3.0.0
Requires-Dist: MarkupSafe ==2.1.3
Requires-Dist: mdurl ==0.1.2
Requires-Dist: more-itertools ==10.1.0
Requires-Dist: mpmath ==1.3.0
Requires-Dist: multidict ==6.0.4
Requires-Dist: nest-asyncio ==1.5.7
Requires-Dist: networkx ==3.1
Requires-Dist: nltk ==3.8.1
Requires-Dist: numba ==0.57.1
Requires-Dist: numpy ==1.24.4
Requires-Dist: openai ==0.27.8
Requires-Dist: packaging ==23.1
Requires-Dist: pandas ==2.0.3
Requires-Dist: Pillow ==10.0.0
Requires-Dist: pkginfo ==1.9.6
Requires-Dist: plotly ==5.16.0
Requires-Dist: prompt-toolkit ==3.0.39
Requires-Dist: pydantic ==1.10.12
Requires-Dist: Pygments ==2.16.1
Requires-Dist: pynndescent ==0.5.10
Requires-Dist: python-dateutil ==2.8.2
Requires-Dist: pytz ==2023.3
Requires-Dist: PyYAML ==6.0.1
Requires-Dist: readme-renderer ==40.0
Requires-Dist: regex ==2023.8.8
Requires-Dist: requests ==2.31.0
Requires-Dist: requests-toolbelt ==1.0.0
Requires-Dist: retrying ==1.3.4
Requires-Dist: rfc3986 ==2.0.0
Requires-Dist: rich ==13.5.2
Requires-Dist: safetensors ==0.3.2
Requires-Dist: scikit-learn ==1.3.0
Requires-Dist: scipy ==1.11.1
Requires-Dist: sentence-transformers ==2.2.2
Requires-Dist: sentencepiece ==0.1.99
Requires-Dist: six ==1.16.0
Requires-Dist: sympy ==1.12
Requires-Dist: tenacity ==8.2.3
Requires-Dist: threadpoolctl ==3.2.0
Requires-Dist: tiktoken ==0.4.0
Requires-Dist: tokenizers ==0.13.3
Requires-Dist: torch ==2.0.1
Requires-Dist: torchvision ==0.15.2
Requires-Dist: tqdm ==4.66.1
Requires-Dist: transformers ==4.31.0
Requires-Dist: twine ==4.0.2
Requires-Dist: typing-extensions ==4.7.1
Requires-Dist: tzdata ==2023.3
Requires-Dist: umap-learn ==0.5.3
Requires-Dist: urllib3 ==2.0.4
Requires-Dist: wcwidth ==0.2.6
Requires-Dist: webencodings ==0.5.1
Requires-Dist: Werkzeug ==2.2.3
Requires-Dist: yarl ==1.9.2
Requires-Dist: zipp ==3.16.2
